github_storage/__init__.py
github_storage/apps.py
github_storage/backends.py
github_storage/migrations/__init__.py
django_github_storages-0.3.2.dist-info/METADATA
django_github_storages-0.3.2.dist-info/WHEEL
django_github_storages-0.3.2.dist-info/LICENSE
django_github_storages-0.3.2.dist-info/RECORD
