Metadata-Version: 2.1
Name: django-github-storages
Version: 0.3.2
Summary: A Django file storage backend that leverages GitHub.
Home-page: https://github.com/arunim-io/django-github-storage
License: BSD-3-Clause
Author: Mugdha Arunim Ahmed
Author-email: mugdhaarunimahmed2017@gmail.com
Requires-Python: >=3.8
Classifier: Development Status :: 5 - Production/Stable
Classifier: Environment :: Web Environment
Classifier: Framework :: Django
Classifier: Framework :: Django :: 3.2
Classifier: Framework :: Django :: 4.0
Classifier: Framework :: Django :: 4.1
Classifier: Intended Audience :: Developers
Classifier: License :: OSI Approved :: BSD License
Classifier: Operating System :: OS Independent
Classifier: Programming Language :: Python
Classifier: Programming Language :: Python :: 3
Classifier: Programming Language :: Python :: 3.8
Classifier: Programming Language :: Python :: 3.9
Classifier: Programming Language :: Python :: 3.10
Classifier: Programming Language :: Python :: 3.11
Classifier: Programming Language :: Python :: 3
Classifier: Programming Language :: Python :: 3.10
Classifier: Programming Language :: Python :: 3.11
Classifier: Programming Language :: Python :: 3.6
Classifier: Programming Language :: Python :: 3.7
Classifier: Programming Language :: Python :: 3.8
Classifier: Programming Language :: Python :: 3.9
Requires-Dist: Django (>=4.1.5,<5.0.0)
Requires-Dist: requests (>=2) ; python_version >= "3.8" and python_version < "4"
Requires-Dist: simplejson (>=3.18.1,<4.0.0)
Project-URL: Repository, https://github.com/arunim-io/django-github-storage
